{"_type":"export","__export_format":4,"__export_date":"2023-04-30T10:00:07.547Z","__export_source":"insomnia.desktop.app:v2023.2.0","resources":[{"_id":"req_ebf0acb2d61048d183e8b255c53998fa","parentId":"fld_8015c665a2fb4f328a37bec8e6250b0a","modified":1682511250730,"created":1682511221243,"url":"{{baseurl}}/tags/list","name":"list","description":"","method":"GET","body":{},"parameters":[],"headers":[],"authentication":{},"metaSortKey":-1682511221243,"isPrivate":false,"settingStoreCookies":true,"settingSendCookies":true,"settingDisableRenderRequestBody":false,"settingEncodeUrl":true,"settingRebuildPath":true,"settingFollowRedirects":"global","_type":"request"},{"_id":"fld_8015c665a2fb4f328a37bec8e6250b0a","parentId":"wrk_065be437a9db4175a5f52764e65c0aee","modified":1682511220192,"created":1682511220192,"name":"Tags","description":"","environment":{},"environmentPropertyOrder":null,"metaSortKey":-1682511220192,"_type":"request_group"},{"_id":"wrk_065be437a9db4175a5f52764e65c0aee","parentId":null,"modified":1682339034214,"created":1682339034214,"name":"file-server","description":"","scope":"collection","_type":"workspace"},{"_id":"req_63ad5a46ca66400f81b4ff2eedc2dcf6","parentId":"fld_8015c665a2fb4f328a37bec8e6250b0a","modified":1682844505118,"created":1682844499139,"url":"{{baseurl}}/tags/delete/1","name":"delete","description":"","method":"DELETE","body":{},"parameters":[],"headers":[],"authentication":{},"metaSortKey":-1682511221218,"isPrivate":false,"settingStoreCookies":true,"settingSendCookies":true,"settingDisableRenderRequestBody":false,"settingEncodeUrl":true,"settingRebuildPath":true,"settingFollowRedirects":"global","_type":"request"},{"_id":"req_1d7154745a3b49faa261fd216221d347","parentId":"fld_8015c665a2fb4f328a37bec8e6250b0a","modified":1682844285126,"created":1682836095677,"url":"{{baseurl}}/tags/add","name":"new","description":"","method":"POST","body":{"mimeType":"application/json","text":"{\n\t\"name\": \"document2\",\n\t\"color\": \"#ff0000\"\n}"},"parameters":[],"headers":[{"name":"Content-Type","value":"application/json"}],"authentication":{},"metaSortKey":-1682511221193,"isPrivate":false,"settingStoreCookies":true,"settingSendCookies":true,"settingDisableRenderRequestBody":false,"settingEncodeUrl":true,"settingRebuildPath":true,"settingFollowRedirects":"global","_type":"request"},{"_id":"req_8ad85c29f9044aa6aedbac9558a48d4b","parentId":"fld_7a38c13577224f68ae643b0d2c1c56d8","modified":1682846812111,"created":1682845705781,"url":"{{baseurl}}/files/add-meta","name":"add Metadata to file","description":"","method":"PUT","body":{"mimeType":"application/json","text":"{\n\t\"fileId\": 2,\n\t\"key\": \"category\",\n\t\"value\": \"documents/pdf\"\n}"},"parameters":[],"headers":[{"name":"Content-Type","value":"application/json"}],"authentication":{},"metaSortKey":-1682845696568,"isPrivate":false,"settingStoreCookies":true,"settingSendCookies":true,"settingDisableRenderRequestBody":false,"settingEncodeUrl":true,"settingRebuildPath":true,"settingFollowRedirects":"global","_type":"request"},{"_id":"fld_7a38c13577224f68ae643b0d2c1c56d8","parentId":"fld_39258f10c2a44f05a597a733f9fed345","modified":1682845695338,"created":1682845695338,"name":"metadata","description":"","environment":{},"environmentPropertyOrder":null,"metaSortKey":-1682845695338,"_type":"request_group"},{"_id":"fld_39258f10c2a44f05a597a733f9fed345","parentId":"wrk_065be437a9db4175a5f52764e65c0aee","modified":1682495416628,"created":1682495416628,"name":"files","description":"","environment":{},"environmentPropertyOrder":null,"metaSortKey":-1682495416628,"_type":"request_group"},{"_id":"req_e3d5b38157e64b2c83fdaf9d8eedf50f","parentId":"fld_7a38c13577224f68ae643b0d2c1c56d8","modified":1682846773518,"created":1682846493014,"url":"{{baseurl}}/files/remove-meta","name":"remove Metadata from file","description":"","method":"PUT","body":{"mimeType":"application/json","text":"{\n\t\"fileId\": 2,\n\t\"key\": \"category\"\n}"},"parameters":[],"headers":[{"name":"Content-Type","value":"application/json"}],"authentication":{},"metaSortKey":-1682845430768,"isPrivate":false,"settingStoreCookies":true,"settingSendCookies":true,"settingDisableRenderRequestBody":false,"settingEncodeUrl":true,"settingRebuildPath":true,"settingFollowRedirects":"global","_type":"request"},{"_id":"req_ce14fe57b1954252a85639754055ed0f","parentId":"fld_3d9a7b18f656483698b1580053f19bf8","modified":1682845687116,"created":1682845164968,"url":"{{baseurl}}/files/add-tag","name":"add Tag to file","description":"","method":"PUT","body":{"mimeType":"application/json","text":"{\n\t\"fileId\": 2,\n\t\"tagName\": \"document2\"\n}"},"parameters":[],"headers":[{"name":"Content-Type","value":"application/json"}],"authentication":{},"metaSortKey":-1682845164968,"isPrivate":false,"settingStoreCookies":true,"settingSendCookies":true,"settingDisableRenderRequestBody":false,"settingEncodeUrl":true,"settingRebuildPath":true,"settingFollowRedirects":"global","_type":"request"},{"_id":"fld_3d9a7b18f656483698b1580053f19bf8","parentId":"fld_39258f10c2a44f05a597a733f9fed345","modified":1682845685360,"created":1682845685360,"name":"tags","description":"","environment":{},"environmentPropertyOrder":null,"metaSortKey":-1682845685360,"_type":"request_group"},{"_id":"req_2aa1d814d3244802a63563557cb6a29d","parentId":"fld_3d9a7b18f656483698b1580053f19bf8","modified":1682845688907,"created":1682845628998,"url":"{{baseurl}}/files/remove-tag","name":"remove tag from file","description":"","method":"PUT","body":{"mimeType":"application/json","text":"{\n\t\"fileId\": 2,\n\t\"tagName\": \"document2\"\n}"},"parameters":[],"headers":[{"name":"Content-Type","value":"application/json"}],"authentication":{},"metaSortKey":-1682845164918,"isPrivate":false,"settingStoreCookies":true,"settingSendCookies":true,"settingDisableRenderRequestBody":false,"settingEncodeUrl":true,"settingRebuildPath":true,"settingFollowRedirects":"global","_type":"request"},{"_id":"req_3a3fb43fa56f4a529ab51549c40b4324","parentId":"fld_39258f10c2a44f05a597a733f9fed345","modified":1682495418874,"created":1682339039690,"url":"{{baseurl}}/files/list","name":"list","description":"","method":"GET","body":{},"parameters":[],"headers":[],"authentication":{},"metaSortKey":-1682339039690,"isPrivate":false,"settingStoreCookies":true,"settingSendCookies":true,"settingDisableRenderRequestBody":false,"settingEncodeUrl":true,"settingRebuildPath":true,"settingFollowRedirects":"global","_type":"request"},{"_id":"req_1d354534bf33476f994bd1a517df52dd","parentId":"fld_39258f10c2a44f05a597a733f9fed345","modified":1682847144782,"created":1682509543749,"url":"{{baseurl}}/files/delete/2","name":"delete","description":"","method":"DELETE","body":{},"parameters":[],"headers":[],"authentication":{},"metaSortKey":-1682339039677.5,"isPrivate":false,"settingStoreCookies":true,"settingSendCookies":true,"settingDisableRenderRequestBody":false,"settingEncodeUrl":true,"settingRebuildPath":true,"settingFollowRedirects":"global","_type":"request"},{"_id":"req_14e6a677e37345bbb3873e9cc505e7a8","parentId":"fld_39258f10c2a44f05a597a733f9fed345","modified":1682495535780,"created":1682495477228,"url":"{{baseurl}}/files/upload","name":"upload","description":"","method":"POST","body":{"mimeType":"multipart/form-data","params":[{"id":"pair_c0cbcfcde8764ce2b53f99ba750f1ee0","name":"file","value":"","description":"","type":"file","fileName":"/home/tim/Downloads/CMVAS-structure.pdf"}]},"parameters":[],"headers":[{"name":"Content-Type","value":"multipart/form-data"}],"authentication":{},"metaSortKey":-1682339039665,"isPrivate":false,"settingStoreCookies":true,"settingSendCookies":true,"settingDisableRenderRequestBody":false,"settingEncodeUrl":true,"settingRebuildPath":true,"settingFollowRedirects":"global","_type":"request"},{"_id":"req_47a54548fb284b6f8cfaa19993925750","parentId":"fld_39258f10c2a44f05a597a733f9fed345","modified":1682845210932,"created":1682495445371,"url":"{{baseurl}}/files/one/2","name":"get one","description":"","method":"GET","body":{},"parameters":[],"headers":[],"authentication":{},"metaSortKey":-1682339039640,"isPrivate":false,"settingStoreCookies":true,"settingSendCookies":true,"settingDisableRenderRequestBody":false,"settingEncodeUrl":true,"settingRebuildPath":true,"settingFollowRedirects":"global","_type":"request"},{"_id":"env_bef80fe1e1ed7e9c4a56f906933ed8ffaf60df95","parentId":"wrk_065be437a9db4175a5f52764e65c0aee","modified":1682339087391,"created":1682339034232,"name":"Base Environment","data":{},"dataPropertyOrder":{},"color":null,"isPrivate":false,"metaSortKey":1682339034232,"_type":"environment"},{"_id":"jar_bef80fe1e1ed7e9c4a56f906933ed8ffaf60df95","parentId":"wrk_065be437a9db4175a5f52764e65c0aee","modified":1682339034240,"created":1682339034240,"name":"Default Jar","cookies":[],"_type":"cookie_jar"},{"_id":"spc_631e7068b90c42079662a80029294102","parentId":"wrk_065be437a9db4175a5f52764e65c0aee","modified":1682339034220,"created":1682339034220,"fileName":"file-server","contents":"","contentType":"yaml","_type":"api_spec"},{"_id":"env_be7f0d89def04be89618cf509b2edaa0","parentId":"env_bef80fe1e1ed7e9c4a56f906933ed8ffaf60df95","modified":1682339096693,"created":1682339088050,"name":"local","data":{"baseurl":"http://localhost:3030"},"dataPropertyOrder":{"&":["baseurl"]},"color":null,"isPrivate":false,"metaSortKey":1682339088050,"_type":"environment"}]}